maol/__init__.py
maol/__main__.py
maol/wid.py
maol-0.0.0.1.dist-info/LICENSE
maol-0.0.0.1.dist-info/METADATA
maol-0.0.0.1.dist-info/WHEEL
maol-0.0.0.1.dist-info/top_level.txt
maol-0.0.0.1.dist-info/RECORD
