Metadata-Version: 2.1
Name: maol
Version: 0.0.0.1
Summary: Model Assisted Object Labeling Toolkit
Author: Matthew Sessions
License: UNKNOWN
Platform: UNKNOWN
License-File: LICENSE
Requires-Dist: PySide6
